drake_eq/__init__.py
drake_eq/__main__.py
drake_eq/equation.py
drake_eq-1.0.0.dist-info/LICENSE
drake_eq-1.0.0.dist-info/METADATA
drake_eq-1.0.0.dist-info/WHEEL
drake_eq-1.0.0.dist-info/RECORD
