Metadata-Version: 2.1
Name: drake-eq
Version: 1.0.0
Summary: drake_eq is a Python implementation of the Drake equation
Home-page: https://github.com/Navid-JL/drake_eq
License: MIT
Keywords: astronomy,drake_equation,frank_drake,SETI
Author: Navid
Author-email: navidjalili3@gmail.com
Requires-Python: >=3.11,<4.0
Classifier: License :: OSI Approved :: MIT License
Classifier: Programming Language :: Python
Classifier: Programming Language :: Python :: 3
Classifier: Programming Language :: Python :: 3.11
Project-URL: Repository, https://github.com/Navid-JL/drake_eq
